swap_i3_workspaces/__init__.py
swap_i3_workspaces/main.py
swap_i3_workspaces-0.2.1.dist-info/LICENSE
swap_i3_workspaces-0.2.1.dist-info/METADATA
swap_i3_workspaces-0.2.1.dist-info/WHEEL
swap_i3_workspaces-0.2.1.dist-info/entry_points.txt
swap_i3_workspaces-0.2.1.dist-info/top_level.txt
swap_i3_workspaces-0.2.1.dist-info/RECORD
